altdss/AltDSS.py
altdss/ArrayProxy.py
altdss/AutoTrans.py
altdss/Batch.py
altdss/Bus.py
altdss/CNData.py
altdss/CapControl.py
altdss/Capacitor.py
altdss/CircuitElement.py
altdss/ControlQueue.py
altdss/DSSObj.py
altdss/DynamicExp.py
altdss/ESPVLControl.py
altdss/EnergyMeter.py
altdss/EnergyMeterExtras.py
altdss/Error.py
altdss/ExpControl.py
altdss/Fault.py
altdss/Fuse.py
altdss/GICLine.py
altdss/GICTransformer.py
altdss/GICsource.py
altdss/GenDispatcher.py
altdss/Generator.py
altdss/GrowthShape.py
altdss/IndMach012.py
altdss/InvControl.py
altdss/Isource.py
altdss/Line.py
altdss/LineCode.py
altdss/LineGeometry.py
altdss/LineSpacing.py
altdss/Load.py
altdss/LoadShape.py
altdss/LoadShapeExtras.py
altdss/Monitor.py
altdss/MonitorExtras.py
altdss/Obj.py
altdss/PCElement.py
altdss/PDElement.py
altdss/PVSystem.py
altdss/PriceShape.py
altdss/Reactor.py
altdss/Recloser.py
altdss/ReduceCkt.py
altdss/RegControl.py
altdss/Relay.py
altdss/Sensor.py
altdss/Settings.py
altdss/Solution.py
altdss/Spectrum.py
altdss/Storage.py
altdss/StorageController.py
altdss/SwtControl.py
altdss/TCC_Curve.py
altdss/TSData.py
altdss/TShape.py
altdss/Topology.py
altdss/Transformer.py
altdss/TransformerExtras.py
altdss/UPFC.py
altdss/UPFCControl.py
altdss/VCCS.py
altdss/VSConverter.py
altdss/Vsource.py
altdss/WireData.py
altdss/XYcurve.py
altdss/XfmrCode.py
altdss/YMatrix.py
altdss/ZIP.py
altdss/__init__.py
altdss/_version.py
altdss/common.py
altdss/enums.py
altdss/types.py
altdss-0.2.4.dist-info/METADATA
altdss-0.2.4.dist-info/WHEEL
altdss-0.2.4.dist-info/licenses/LICENSE
altdss-0.2.4.dist-info/RECORD
