Metadata-Version: 2.1
Name: altdss
Version: 0.2.4
Summary: Modern, detailed Python interface/bindings and tools based on the AltDSS/DSS C-API project, the alternative OpenDSS implementation from DSS-Extensions.org. Tries to expose all OpenDSS objects, bulk operations and many details which previously required using the Text interface, or just weren't available.
Project-URL: Homepage, https://github.com/dss-extensions/AltDSS-Python
Project-URL: Documentation, https://dss-extensions.org/AltDSS-Python
Project-URL: Repository, https://github.com/dss-extensions/AltDSS-Python.git
Project-URL: Bug Tracker, https://github.com/dss-extensions/AltDSS-Python/issues
Project-URL: Changelog, https://github.com/dss-extensions/AltDSS-Python/blob/main/docs/changelog.md
Author-email: Paulo Meira <pmeira@ieee.org>, Dheepak Krishnamurthy <me@kdheepak.com>
Maintainer-email: Paulo Meira <pmeira@ieee.org>
License: BSD 3-Clause License
License-File: LICENSE
Keywords: altdss,electric power systems,opendss,opendssdirect,powerflow,short-circuit
Classifier: Development Status :: 4 - Beta
Classifier: Intended Audience :: Education
Classifier: Intended Audience :: Science/Research
Classifier: License :: OSI Approved :: BSD License
Classifier: Programming Language :: Python :: 3.7
Classifier: Programming Language :: Python :: 3.8
Classifier: Programming Language :: Python :: 3.9
Classifier: Programming Language :: Python :: 3.10
Classifier: Programming Language :: Python :: 3.11
Classifier: Programming Language :: Python :: 3.12
Classifier: Programming Language :: Python :: Implementation :: CPython
Classifier: Programming Language :: Python :: Implementation :: PyPy
Classifier: Topic :: Scientific/Engineering
Requires-Python: >=3.7
Requires-Dist: dss-python
Requires-Dist: dss-python-backend==0.14.5
Requires-Dist: numpy>=1.21.0
Requires-Dist: pandas
Requires-Dist: scipy
Requires-Dist: typing-extensions<5,>=4.5
Provides-Extra: all
Requires-Dist: dss-python[all]; extra == 'all'
Provides-Extra: test
Requires-Dist: pytest; extra == 'test'
Requires-Dist: ruff; extra == 'test'
Requires-Dist: xmldiff; extra == 'test'
